{
  "withFriends": false,
  "nodes": [
    {
      "group": 2,
      "id": "jon",
      "weight": 0.05463212875010377
    },
    {
      "group": 5,
      "id": "arya",
      "weight": 0.027574782552875054
    },
    {
      "group": 3,
      "id": "sansa",
      "weight": 0.048845213127920825
    },
    {
      "group": 3,
      "id": "robert",
      "weight": 0.025099957229039033
    },
    {
      "group": 3,
      "id": "pycelle",
      "weight": 0.006907745162354637
    },
    {
      "group": 5,
      "id": "robb",
      "weight": 0.0414898305608573
    },
    {
      "group": 5,
      "id": "theon",
      "weight": 0.00812745590136669
    },
    {
      "group": 3,
      "id": "tyrion",
      "weight": 0.06571706197642573
    },
    {
      "group": 3,
      "id": "tywin",
      "weight": 0.026167131407265717
    },
    {
      "group": 2,
      "id": "ghost",
      "weight": 0.009230449675271342
    },
    {
      "group": 1,
      "id": "missandei",
      "weight": 0.007096984460817612
    },
    {
      "group": 3,
      "id": "cersei",
      "weight": 0.030015127762408486
    },
    {
      "group": 0,
      "id": "nymeria",
      "weight": 0.003258469731590588
    },
    {
      "group": 3,
      "id": "jaime",
      "weight": 0.036670146576783684
    },
    {
      "group": 2,
      "id": "wildling",
      "weight": 0.012007677304042227
    },
    {
      "group": 2,
      "id": "walkers",
      "weight": 0.0026719299816705118
    },
    {
      "group": 3,
      "id": "joffrey",
      "weight": 0.035645905666208746
    },
    {
      "group": 5,
      "id": "ned",
      "weight": 0.015929097923516863
    },
    {
      "group": 3,
      "id": "varys",
      "weight": 0.014601719017346217
    },
    {
      "group": 3,
      "id": "shae",
      "weight": 0.009482580359534568
    },
    {
      "group": 5,
      "id": "ramsay",
      "weight": 0.0035745296584417242
    },
    {
      "group": 5,
      "id": "roose",
      "weight": 0.006907268746041526
    },
    {
      "group": 4,
      "id": "shireen",
      "weight": 0.004353310018357269
    },
    {
      "group": 1,
      "id": "daario",
      "weight": 0.00921049124198079
    },
    {
      "group": 5,
      "id": "catelyn",
      "weight": 0.03086660875842771
    },
    {
      "group": 0,
      "id": "bran",
      "weight": 0.036079297447008836
    },
    {
      "group": 2,
      "id": "mance",
      "weight": 0.018558831327443015
    },
    {
      "group": 3,
      "id": "margaery",
      "weight": 0.01420026321989026
    },
    {
      "group": 4,
      "id": "melisandre",
      "weight": 0.011904253400968625
    },
    {
      "group": 4,
      "id": "stannis",
      "weight": 0.027224456043586292
    },
    {
      "group": 1,
      "id": "drogo",
      "weight": 0.011263312685448898
    },
    {
      "group": 5,
      "id": "jeyne",
      "weight": 0.00969181340912803
    },
    {
      "group": 0,
      "id": "hodor",
      "weight": 0.023121628598518698
    },
    {
      "group": 5,
      "id": "rickon",
      "weight": 0.010912701242720233
    },
    {
      "group": 3,
      "id": "renly",
      "weight": 0.011622565690820773
    },
    {
      "group": 3,
      "id": "faceless",
      "weight": 0.0027970085878216006
    },
    {
      "group": 3,
      "id": "tommen",
      "weight": 0.011310240692916371
    },
    {
      "group": 3,
      "id": "myranda",
      "weight": 0.002864301876642116
    },
    {
      "group": 1,
      "id": "worm",
      "weight": 0.006083286556196717
    },
    {
      "group": 3,
      "id": "gregor",
      "weight": 0.011816541073539138
    },
    {
      "group": 5,
      "id": "sandor",
      "weight": 0.015605586519803974
    },
    {
      "group": 3,
      "id": "oberyn",
      "weight": 0.011957776726798344
    },
    {
      "group": 5,
      "id": "edmure",
      "weight": 0.015026458839502904
    },
    {
      "group": 2,
      "id": "craster",
      "weight": 0.012234522269362214
    },
    {
      "group": 0,
      "id": "osha",
      "weight": 0.00322934539858227
    },
    {
      "group": 3,
      "id": "bronn",
      "weight": 0.010555507771065778
    },
    {
      "group": 2,
      "id": "ygritte",
      "weight": 0.013111904597252205
    },
    {
      "group": 2,
      "id": "sam",
      "weight": 0.029952685680141877
    },
    {
      "group": 1,
      "id": "khaleesi",
      "weight": 0.011303721986768508
    },
    {
      "group": 4,
      "id": "davos",
      "weight": 0.01529317532806167
    },
    {
      "group": 5,
      "id": "walder",
      "weight": 0.018173112273613817
    },
    {
      "group": 3,
      "id": "lysa",
      "weight": 0.014950968202345039
    },
    {
      "group": 3,
      "id": "petyr",
      "weight": 0.017812571693974856
    },
    {
      "group": 1,
      "id": "barristan",
      "weight": 0.007187871842490008
    },
    {
      "group": 1,
      "id": "jorah",
      "weight": 0.016327694877439285
    },
    {
      "group": 0,
      "id": "meera",
      "weight": 0.017214298123683875
    },
    {
      "group": 2,
      "id": "gilly",
      "weight": 0.013484176689272903
    },
    {
      "group": 3,
      "id": "loras",
      "weight": 0.011044515776542177
    }
  ],
  "links": [
    {
      "source": 0,
      "target": 1,
      "value": 36
    },
    {
      "source": 0,
      "target": 2,
      "value": 16
    },
    {
      "source": 0,
      "target": 3,
      "value": 37
    },
    {
      "source": 0,
      "target": 5,
      "value": 43
    },
    {
      "source": 0,
      "target": 6,
      "value": 21
    },
    {
      "source": 0,
      "target": 7,
      "value": 14
    },
    {
      "source": 0,
      "target": 8,
      "value": 6
    },
    {
      "source": 0,
      "target": 9,
      "value": 67
    },
    {
      "source": 0,
      "target": 11,
      "value": 6
    },
    {
      "source": 0,
      "target": 13,
      "value": 10
    },
    {
      "source": 0,
      "target": 14,
      "value": 92
    },
    {
      "source": 0,
      "target": 16,
      "value": 4
    },
    {
      "source": 0,
      "target": 17,
      "value": 30
    },
    {
      "source": 0,
      "target": 24,
      "value": 11
    },
    {
      "source": 0,
      "target": 25,
      "value": 37
    },
    {
      "source": 0,
      "target": 26,
      "value": 236
    },
    {
      "source": 0,
      "target": 28,
      "value": 26
    },
    {
      "source": 0,
      "target": 29,
      "value": 40
    },
    {
      "source": 0,
      "target": 32,
      "value": 6
    },
    {
      "source": 0,
      "target": 33,
      "value": 15
    },
    {
      "source": 0,
      "target": 40,
      "value": 5
    },
    {
      "source": 0,
      "target": 42,
      "value": 5
    },
    {
      "source": 0,
      "target": 43,
      "value": 26
    },
    {
      "source": 0,
      "target": 46,
      "value": 169
    },
    {
      "source": 0,
      "target": 47,
      "value": 143
    },
    {
      "source": 0,
      "target": 49,
      "value": 4
    },
    {
      "source": 0,
      "target": 51,
      "value": 21
    },
    {
      "source": 0,
      "target": 52,
      "value": 12
    },
    {
      "source": 0,
      "target": 53,
      "value": 8
    },
    {
      "source": 0,
      "target": 55,
      "value": 10
    },
    {
      "source": 0,
      "target": 56,
      "value": 36
    },
    {
      "source": 1,
      "target": 2,
      "value": 54
    },
    {
      "source": 1,
      "target": 3,
      "value": 30
    },
    {
      "source": 1,
      "target": 5,
      "value": 46
    },
    {
      "source": 1,
      "target": 7,
      "value": 19
    },
    {
      "source": 1,
      "target": 11,
      "value": 10
    },
    {
      "source": 1,
      "target": 12,
      "value": 4
    },
    {
      "source": 1,
      "target": 13,
      "value": 29
    },
    {
      "source": 1,
      "target": 16,
      "value": 25
    },
    {
      "source": 1,
      "target": 17,
      "value": 39
    },
    {
      "source": 1,
      "target": 18,
      "value": 6
    },
    {
      "source": 1,
      "target": 21,
      "value": 12
    },
    {
      "source": 1,
      "target": 24,
      "value": 28
    },
    {
      "source": 1,
      "target": 25,
      "value": 21
    },
    {
      "source": 1,
      "target": 31,
      "value": 6
    },
    {
      "source": 1,
      "target": 33,
      "value": 13
    },
    {
      "source": 1,
      "target": 34,
      "value": 5
    },
    {
      "source": 1,
      "target": 39,
      "value": 11
    },
    {
      "source": 1,
      "target": 40,
      "value": 161
    },
    {
      "source": 1,
      "target": 42,
      "value": 7
    },
    {
      "source": 1,
      "target": 46,
      "value": 5
    },
    {
      "source": 1,
      "target": 50,
      "value": 11
    },
    {
      "source": 2,
      "target": 3,
      "value": 40
    },
    {
      "source": 2,
      "target": 5,
      "value": 50
    },
    {
      "source": 2,
      "target": 6,
      "value": 4
    },
    {
      "source": 2,
      "target": 7,
      "value": 205
    },
    {
      "source": 2,
      "target": 8,
      "value": 17
    },
    {
      "source": 2,
      "target": 11,
      "value": 61
    },
    {
      "source": 2,
      "target": 13,
      "value": 31
    },
    {
      "source": 2,
      "target": 16,
      "value": 119
    },
    {
      "source": 2,
      "target": 17,
      "value": 23
    },
    {
      "source": 2,
      "target": 18,
      "value": 14
    },
    {
      "source": 2,
      "target": 19,
      "value": 36
    },
    {
      "source": 2,
      "target": 24,
      "value": 36
    },
    {
      "source": 2,
      "target": 25,
      "value": 27
    },
    {
      "source": 2,
      "target": 27,
      "value": 100
    },
    {
      "source": 2,
      "target": 29,
      "value": 10
    },
    {
      "source": 2,
      "target": 33,
      "value": 15
    },
    {
      "source": 2,
      "target": 34,
      "value": 12
    },
    {
      "source": 2,
      "target": 36,
      "value": 13
    },
    {
      "source": 2,
      "target": 40,
      "value": 28
    },
    {
      "source": 2,
      "target": 41,
      "value": 13
    },
    {
      "source": 2,
      "target": 42,
      "value": 4
    },
    {
      "source": 2,
      "target": 51,
      "value": 79
    },
    {
      "source": 2,
      "target": 52,
      "value": 96
    },
    {
      "source": 2,
      "target": 57,
      "value": 41
    },
    {
      "source": 3,
      "target": 5,
      "value": 4
    },
    {
      "source": 3,
      "target": 7,
      "value": 38
    },
    {
      "source": 3,
      "target": 8,
      "value": 28
    },
    {
      "source": 3,
      "target": 11,
      "value": 42
    },
    {
      "source": 3,
      "target": 13,
      "value": 45
    },
    {
      "source": 3,
      "target": 16,
      "value": 17
    },
    {
      "source": 3,
      "target": 17,
      "value": 22
    },
    {
      "source": 3,
      "target": 18,
      "value": 6
    },
    {
      "source": 3,
      "target": 24,
      "value": 7
    },
    {
      "source": 3,
      "target": 25,
      "value": 6
    },
    {
      "source": 3,
      "target": 28,
      "value": 6
    },
    {
      "source": 3,
      "target": 29,
      "value": 24
    },
    {
      "source": 3,
      "target": 30,
      "value": 4
    },
    {
      "source": 3,
      "target": 34,
      "value": 10
    },
    {
      "source": 3,
      "target": 36,
      "value": 4
    },
    {
      "source": 3,
      "target": 37,
      "value": 4
    },
    {
      "source": 3,
      "target": 40,
      "value": 12
    },
    {
      "source": 3,
      "target": 41,
      "value": 5
    },
    {
      "source": 3,
      "target": 42,
      "value": 5
    },
    {
      "source": 3,
      "target": 48,
      "value": 4
    },
    {
      "source": 3,
      "target": 49,
      "value": 10
    },
    {
      "source": 3,
      "target": 50,
      "value": 6
    },
    {
      "source": 3,
      "target": 51,
      "value": 29
    },
    {
      "source": 3,
      "target": 52,
      "value": 20
    },
    {
      "source": 3,
      "target": 53,
      "value": 14
    },
    {
      "source": 3,
      "target": 54,
      "value": 4
    },
    {
      "source": 4,
      "target": 7,
      "value": 32
    },
    {
      "source": 4,
      "target": 8,
      "value": 13
    },
    {
      "source": 4,
      "target": 11,
      "value": 13
    },
    {
      "source": 4,
      "target": 16,
      "value": 12
    },
    {
      "source": 4,
      "target": 18,
      "value": 17
    },
    {
      "source": 4,
      "target": 52,
      "value": 4
    },
    {
      "source": 5,
      "target": 6,
      "value": 24
    },
    {
      "source": 5,
      "target": 7,
      "value": 32
    },
    {
      "source": 5,
      "target": 8,
      "value": 36
    },
    {
      "source": 5,
      "target": 11,
      "value": 12
    },
    {
      "source": 5,
      "target": 13,
      "value": 48
    },
    {
      "source": 5,
      "target": 16,
      "value": 28
    },
    {
      "source": 5,
      "target": 17,
      "value": 41
    },
    {
      "source": 5,
      "target": 20,
      "value": 5
    },
    {
      "source": 5,
      "target": 21,
      "value": 15
    },
    {
      "source": 5,
      "target": 24,
      "value": 169
    },
    {
      "source": 5,
      "target": 25,
      "value": 42
    },
    {
      "source": 5,
      "target": 26,
      "value": 4
    },
    {
      "source": 5,
      "target": 27,
      "value": 6
    },
    {
      "source": 5,
      "target": 29,
      "value": 12
    },
    {
      "source": 5,
      "target": 31,
      "value": 60
    },
    {
      "source": 5,
      "target": 32,
      "value": 11
    },
    {
      "source": 5,
      "target": 33,
      "value": 25
    },
    {
      "source": 5,
      "target": 36,
      "value": 4
    },
    {
      "source": 5,
      "target": 39,
      "value": 6
    },
    {
      "source": 5,
      "target": 42,
      "value": 89
    },
    {
      "source": 5,
      "target": 47,
      "value": 5
    },
    {
      "source": 5,
      "target": 50,
      "value": 101
    },
    {
      "source": 5,
      "target": 51,
      "value": 11
    },
    {
      "source": 5,
      "target": 52,
      "value": 19
    },
    {
      "source": 5,
      "target": 56,
      "value": 4
    },
    {
      "source": 6,
      "target": 7,
      "value": 4
    },
    {
      "source": 6,
      "target": 17,
      "value": 6
    },
    {
      "source": 6,
      "target": 24,
      "value": 11
    },
    {
      "source": 6,
      "target": 25,
      "value": 21
    },
    {
      "source": 6,
      "target": 33,
      "value": 11
    },
    {
      "source": 6,
      "target": 50,
      "value": 11
    },
    {
      "source": 6,
      "target": 55,
      "value": 4
    },
    {
      "source": 7,
      "target": 8,
      "value": 149
    },
    {
      "source": 7,
      "target": 9,
      "value": 6
    },
    {
      "source": 7,
      "target": 11,
      "value": 143
    },
    {
      "source": 7,
      "target": 13,
      "value": 108
    },
    {
      "source": 7,
      "target": 16,
      "value": 169
    },
    {
      "source": 7,
      "target": 17,
      "value": 6
    },
    {
      "source": 7,
      "target": 18,
      "value": 68
    },
    {
      "source": 7,
      "target": 19,
      "value": 72
    },
    {
      "source": 7,
      "target": 21,
      "value": 5
    },
    {
      "source": 7,
      "target": 24,
      "value": 14
    },
    {
      "source": 7,
      "target": 25,
      "value": 12
    },
    {
      "source": 7,
      "target": 27,
      "value": 43
    },
    {
      "source": 7,
      "target": 29,
      "value": 25
    },
    {
      "source": 7,
      "target": 31,
      "value": 5
    },
    {
      "source": 7,
      "target": 34,
      "value": 16
    },
    {
      "source": 7,
      "target": 36,
      "value": 34
    },
    {
      "source": 7,
      "target": 39,
      "value": 46
    },
    {
      "source": 7,
      "target": 40,
      "value": 13
    },
    {
      "source": 7,
      "target": 41,
      "value": 79
    },
    {
      "source": 7,
      "target": 42,
      "value": 6
    },
    {
      "source": 7,
      "target": 45,
      "value": 122
    },
    {
      "source": 7,
      "target": 47,
      "value": 5
    },
    {
      "source": 7,
      "target": 50,
      "value": 6
    },
    {
      "source": 7,
      "target": 51,
      "value": 17
    },
    {
      "source": 7,
      "target": 52,
      "value": 34
    },
    {
      "source": 7,
      "target": 57,
      "value": 17
    },
    {
      "source": 8,
      "target": 11,
      "value": 48
    },
    {
      "source": 8,
      "target": 13,
      "value": 48
    },
    {
      "source": 8,
      "target": 16,
      "value": 43
    },
    {
      "source": 8,
      "target": 17,
      "value": 6
    },
    {
      "source": 8,
      "target": 18,
      "value": 14
    },
    {
      "source": 8,
      "target": 24,
      "value": 15
    },
    {
      "source": 8,
      "target": 27,
      "value": 5
    },
    {
      "source": 8,
      "target": 29,
      "value": 36
    },
    {
      "source": 8,
      "target": 31,
      "value": 8
    },
    {
      "source": 8,
      "target": 34,
      "value": 5
    },
    {
      "source": 8,
      "target": 36,
      "value": 13
    },
    {
      "source": 8,
      "target": 39,
      "value": 14
    },
    {
      "source": 8,
      "target": 41,
      "value": 16
    },
    {
      "source": 8,
      "target": 42,
      "value": 12
    },
    {
      "source": 8,
      "target": 45,
      "value": 7
    },
    {
      "source": 8,
      "target": 47,
      "value": 4
    },
    {
      "source": 8,
      "target": 49,
      "value": 5
    },
    {
      "source": 8,
      "target": 50,
      "value": 8
    },
    {
      "source": 8,
      "target": 51,
      "value": 10
    },
    {
      "source": 8,
      "target": 52,
      "value": 16
    },
    {
      "source": 9,
      "target": 13,
      "value": 4
    },
    {
      "source": 9,
      "target": 25,
      "value": 4
    },
    {
      "source": 9,
      "target": 26,
      "value": 6
    },
    {
      "source": 9,
      "target": 29,
      "value": 6
    },
    {
      "source": 9,
      "target": 34,
      "value": 10
    },
    {
      "source": 9,
      "target": 46,
      "value": 20
    },
    {
      "source": 9,
      "target": 47,
      "value": 10
    },
    {
      "source": 10,
      "target": 23,
      "value": 6
    },
    {
      "source": 10,
      "target": 30,
      "value": 7
    },
    {
      "source": 10,
      "target": 48,
      "value": 6
    },
    {
      "source": 10,
      "target": 54,
      "value": 6
    },
    {
      "source": 11,
      "target": 13,
      "value": 117
    },
    {
      "source": 11,
      "target": 16,
      "value": 69
    },
    {
      "source": 11,
      "target": 17,
      "value": 7
    },
    {
      "source": 11,
      "target": 18,
      "value": 17
    },
    {
      "source": 11,
      "target": 19,
      "value": 12
    },
    {
      "source": 11,
      "target": 24,
      "value": 8
    },
    {
      "source": 11,
      "target": 27,
      "value": 7
    },
    {
      "source": 11,
      "target": 29,
      "value": 6
    },
    {
      "source": 11,
      "target": 36,
      "value": 17
    },
    {
      "source": 11,
      "target": 39,
      "value": 12
    },
    {
      "source": 11,
      "target": 40,
      "value": 15
    },
    {
      "source": 11,
      "target": 41,
      "value": 15
    },
    {
      "source": 11,
      "target": 42,
      "value": 5
    },
    {
      "source": 11,
      "target": 45,
      "value": 16
    },
    {
      "source": 11,
      "target": 51,
      "value": 8
    },
    {
      "source": 11,
      "target": 52,
      "value": 10
    },
    {
      "source": 11,
      "target": 57,
      "value": 7
    },
    {
      "source": 12,
      "target": 41,
      "value": 4
    },
    {
      "source": 13,
      "target": 16,
      "value": 43
    },
    {
      "source": 13,
      "target": 17,
      "value": 24
    },
    {
      "source": 13,
      "target": 18,
      "value": 16
    },
    {
      "source": 13,
      "target": 21,
      "value": 14
    },
    {
      "source": 13,
      "target": 24,
      "value": 56
    },
    {
      "source": 13,
      "target": 27,
      "value": 9
    },
    {
      "source": 13,
      "target": 29,
      "value": 18
    },
    {
      "source": 13,
      "target": 31,
      "value": 8
    },
    {
      "source": 13,
      "target": 33,
      "value": 4
    },
    {
      "source": 13,
      "target": 34,
      "value": 29
    },
    {
      "source": 13,
      "target": 36,
      "value": 23
    },
    {
      "source": 13,
      "target": 39,
      "value": 16
    },
    {
      "source": 13,
      "target": 40,
      "value": 4
    },
    {
      "source": 13,
      "target": 41,
      "value": 7
    },
    {
      "source": 13,
      "target": 42,
      "value": 19
    },
    {
      "source": 13,
      "target": 49,
      "value": 6
    },
    {
      "source": 13,
      "target": 50,
      "value": 7
    },
    {
      "source": 13,
      "target": 51,
      "value": 4
    },
    {
      "source": 13,
      "target": 52,
      "value": 4
    },
    {
      "source": 13,
      "target": 53,
      "value": 17
    },
    {
      "source": 13,
      "target": 57,
      "value": 41
    },
    {
      "source": 14,
      "target": 26,
      "value": 36
    },
    {
      "source": 14,
      "target": 29,
      "value": 9
    },
    {
      "source": 14,
      "target": 43,
      "value": 23
    },
    {
      "source": 14,
      "target": 46,
      "value": 11
    },
    {
      "source": 14,
      "target": 47,
      "value": 18
    },
    {
      "source": 14,
      "target": 56,
      "value": 14
    },
    {
      "source": 16,
      "target": 17,
      "value": 8
    },
    {
      "source": 16,
      "target": 18,
      "value": 8
    },
    {
      "source": 16,
      "target": 19,
      "value": 6
    },
    {
      "source": 16,
      "target": 27,
      "value": 65
    },
    {
      "source": 16,
      "target": 28,
      "value": 7
    },
    {
      "source": 16,
      "target": 29,
      "value": 33
    },
    {
      "source": 16,
      "target": 34,
      "value": 11
    },
    {
      "source": 16,
      "target": 36,
      "value": 33
    },
    {
      "source": 16,
      "target": 39,
      "value": 15
    },
    {
      "source": 16,
      "target": 40,
      "value": 33
    },
    {
      "source": 16,
      "target": 41,
      "value": 11
    },
    {
      "source": 16,
      "target": 45,
      "value": 9
    },
    {
      "source": 16,
      "target": 49,
      "value": 14
    },
    {
      "source": 16,
      "target": 50,
      "value": 7
    },
    {
      "source": 16,
      "target": 52,
      "value": 13
    },
    {
      "source": 16,
      "target": 57,
      "value": 16
    },
    {
      "source": 17,
      "target": 24,
      "value": 27
    },
    {
      "source": 17,
      "target": 25,
      "value": 12
    },
    {
      "source": 17,
      "target": 29,
      "value": 5
    },
    {
      "source": 17,
      "target": 31,
      "value": 7
    },
    {
      "source": 17,
      "target": 33,
      "value": 15
    },
    {
      "source": 17,
      "target": 39,
      "value": 4
    },
    {
      "source": 17,
      "target": 40,
      "value": 12
    },
    {
      "source": 17,
      "target": 46,
      "value": 6
    },
    {
      "source": 17,
      "target": 51,
      "value": 4
    },
    {
      "source": 17,
      "target": 52,
      "value": 6
    },
    {
      "source": 17,
      "target": 57,
      "value": 4
    },
    {
      "source": 18,
      "target": 19,
      "value": 24
    },
    {
      "source": 18,
      "target": 29,
      "value": 5
    },
    {
      "source": 18,
      "target": 30,
      "value": 4
    },
    {
      "source": 18,
      "target": 34,
      "value": 5
    },
    {
      "source": 18,
      "target": 36,
      "value": 4
    },
    {
      "source": 18,
      "target": 45,
      "value": 11
    },
    {
      "source": 18,
      "target": 52,
      "value": 8
    },
    {
      "source": 18,
      "target": 54,
      "value": 5
    },
    {
      "source": 19,
      "target": 45,
      "value": 4
    },
    {
      "source": 20,
      "target": 21,
      "value": 5
    },
    {
      "source": 20,
      "target": 50,
      "value": 4
    },
    {
      "source": 21,
      "target": 24,
      "value": 13
    },
    {
      "source": 21,
      "target": 50,
      "value": 13
    },
    {
      "source": 22,
      "target": 29,
      "value": 10
    },
    {
      "source": 22,
      "target": 49,
      "value": 19
    },
    {
      "source": 23,
      "target": 30,
      "value": 9
    },
    {
      "source": 23,
      "target": 38,
      "value": 6
    },
    {
      "source": 23,
      "target": 54,
      "value": 17
    },
    {
      "source": 24,
      "target": 25,
      "value": 16
    },
    {
      "source": 24,
      "target": 29,
      "value": 12
    },
    {
      "source": 24,
      "target": 31,
      "value": 31
    },
    {
      "source": 24,
      "target": 33,
      "value": 11
    },
    {
      "source": 24,
      "target": 34,
      "value": 7
    },
    {
      "source": 24,
      "target": 39,
      "value": 6
    },
    {
      "source": 24,
      "target": 40,
      "value": 5
    },
    {
      "source": 24,
      "target": 42,
      "value": 77
    },
    {
      "source": 24,
      "target": 50,
      "value": 81
    },
    {
      "source": 24,
      "target": 51,
      "value": 28
    },
    {
      "source": 24,
      "target": 52,
      "value": 16
    },
    {
      "source": 24,
      "target": 57,
      "value": 4
    },
    {
      "source": 25,
      "target": 31,
      "value": 5
    },
    {
      "source": 25,
      "target": 32,
      "value": 300
    },
    {
      "source": 25,
      "target": 33,
      "value": 41
    },
    {
      "source": 25,
      "target": 36,
      "value": 4
    },
    {
      "source": 25,
      "target": 42,
      "value": 4
    },
    {
      "source": 25,
      "target": 43,
      "value": 4
    },
    {
      "source": 25,
      "target": 44,
      "value": 4
    },
    {
      "source": 25,
      "target": 46,
      "value": 6
    },
    {
      "source": 25,
      "target": 47,
      "value": 43
    },
    {
      "source": 25,
      "target": 50,
      "value": 6
    },
    {
      "source": 25,
      "target": 51,
      "value": 4
    },
    {
      "source": 25,
      "target": 55,
      "value": 153
    },
    {
      "source": 25,
      "target": 56,
      "value": 13
    },
    {
      "source": 26,
      "target": 29,
      "value": 4
    },
    {
      "source": 26,
      "target": 43,
      "value": 19
    },
    {
      "source": 26,
      "target": 46,
      "value": 29
    },
    {
      "source": 26,
      "target": 47,
      "value": 24
    },
    {
      "source": 26,
      "target": 56,
      "value": 14
    },
    {
      "source": 27,
      "target": 34,
      "value": 18
    },
    {
      "source": 27,
      "target": 36,
      "value": 10
    },
    {
      "source": 27,
      "target": 57,
      "value": 26
    },
    {
      "source": 28,
      "target": 29,
      "value": 58
    },
    {
      "source": 28,
      "target": 34,
      "value": 6
    },
    {
      "source": 28,
      "target": 36,
      "value": 5
    },
    {
      "source": 28,
      "target": 47,
      "value": 15
    },
    {
      "source": 28,
      "target": 49,
      "value": 76
    },
    {
      "source": 29,
      "target": 34,
      "value": 38
    },
    {
      "source": 29,
      "target": 36,
      "value": 13
    },
    {
      "source": 29,
      "target": 39,
      "value": 5
    },
    {
      "source": 29,
      "target": 42,
      "value": 8
    },
    {
      "source": 29,
      "target": 45,
      "value": 4
    },
    {
      "source": 29,
      "target": 47,
      "value": 40
    },
    {
      "source": 29,
      "target": 49,
      "value": 102
    },
    {
      "source": 29,
      "target": 52,
      "value": 4
    },
    {
      "source": 29,
      "target": 57,
      "value": 6
    },
    {
      "source": 30,
      "target": 48,
      "value": 9
    },
    {
      "source": 30,
      "target": 54,
      "value": 24
    },
    {
      "source": 31,
      "target": 33,
      "value": 4
    },
    {
      "source": 31,
      "target": 42,
      "value": 6
    },
    {
      "source": 31,
      "target": 50,
      "value": 24
    },
    {
      "source": 32,
      "target": 33,
      "value": 7
    },
    {
      "source": 32,
      "target": 47,
      "value": 31
    },
    {
      "source": 32,
      "target": 50,
      "value": 7
    },
    {
      "source": 32,
      "target": 55,
      "value": 141
    },
    {
      "source": 33,
      "target": 42,
      "value": 4
    },
    {
      "source": 33,
      "target": 44,
      "value": 5
    },
    {
      "source": 33,
      "target": 51,
      "value": 4
    },
    {
      "source": 33,
      "target": 55,
      "value": 4
    },
    {
      "source": 34,
      "target": 36,
      "value": 4
    },
    {
      "source": 34,
      "target": 49,
      "value": 5
    },
    {
      "source": 34,
      "target": 57,
      "value": 28
    },
    {
      "source": 36,
      "target": 41,
      "value": 7
    },
    {
      "source": 36,
      "target": 45,
      "value": 6
    },
    {
      "source": 38,
      "target": 48,
      "value": 5
    },
    {
      "source": 39,
      "target": 40,
      "value": 18
    },
    {
      "source": 39,
      "target": 41,
      "value": 50
    },
    {
      "source": 39,
      "target": 45,
      "value": 11
    },
    {
      "source": 41,
      "target": 45,
      "value": 4
    },
    {
      "source": 42,
      "target": 50,
      "value": 42
    },
    {
      "source": 42,
      "target": 51,
      "value": 8
    },
    {
      "source": 42,
      "target": 52,
      "value": 5
    },
    {
      "source": 43,
      "target": 47,
      "value": 98
    },
    {
      "source": 43,
      "target": 56,
      "value": 47
    },
    {
      "source": 47,
      "target": 55,
      "value": 27
    },
    {
      "source": 47,
      "target": 56,
      "value": 112
    },
    {
      "source": 48,
      "target": 54,
      "value": 26
    },
    {
      "source": 50,
      "target": 52,
      "value": 29
    },
    {
      "source": 51,
      "target": 52,
      "value": 84
    },
    {
      "source": 53,
      "target": 54,
      "value": 9
    },
    {
      "source": 55,
      "target": 56,
      "value": 10
    }
  ]
}